{"summaries":[{"symbol":{"__symbol":0,"members":[]},"metadata":{"__symbolic":"class"},"type":{"summaryKind":1,"type":{"reference":{"__symbol":0,"members":[]},"diDeps":[],"lifecycleHooks":[]},"isComponent":true,"selector":"demo-app","inputs":{"foo":"foo"},"outputs":{},"hostListeners":{},"hostProperties":{},"hostAttributes":{},"providers":[],"viewProviders":[],"queries":[],"entryComponents":[],"changeDetection":1,"template":{"animations":[],"ngContentSelectors":[],"encapsulation":2},"wrapperType":{"__symbol":52,"members":[]},"componentViewType":{"__symbol":53,"members":[]},"componentFactory":{"__symbol":3,"members":[]}}},{"symbol":{"__symbol":1,"members":[]},"metadata":{"__symbolic":"class"},"type":{"summaryKind":2,"type":{"reference":{"__symbol":1,"members":[]},"diDeps":[{"isAttribute":false,"isHost":false,"isSelf":false,"isSkipSelf":false,"isOptional":false,"token":{"identifier":{"reference":{"__symbol":2,"members":[]}}}}],"lifecycleHooks":[]},"entryComponents":[{"componentType":{"__symbol":0,"members":[]},"componentFactory":{"__symbol":3,"members":[]}}],"providers":[{"provider":{"token":{"identifier":{"reference":{"__symbol":4,"members":[]}}},"useClass":{"reference":{"__symbol":5,"members":[]},"diDeps":[{"isAttribute":false,"isHost":false,"isSelf":false,"isSkipSelf":false,"isOptional":false,"token":{"identifier":{"reference":{"__symbol":6,"members":[]}}}}],"lifecycleHooks":[]},"useFactory":null,"useExisting":null,"deps":[{"isAttribute":false,"isHost":false,"isSelf":false,"isSkipSelf":false,"isOptional":false,"token":{"identifier":{"reference":{"__symbol":6,"members":[]}}}}],"multi":false},"module":{"reference":{"__symbol":7,"members":[]},"diDeps":[],"lifecycleHooks":[]}},{"provider":{"token":{"identifier":{"reference":{"__symbol":8,"members":[]},"diDeps":[{"isAttribute":false,"isHost":false,"isSelf":false,"isSkipSelf":false,"isOptional":false,"token":{"identifier":{"reference":{"__symbol":9,"members":[]}}}},{"isAttribute":false,"isHost":false,"isSelf":false,"isSkipSelf":false,"isOptional":false,"token":{"identifier":{"reference":{"__symbol":10,"members":[]}}}},{"isAttribute":false,"isHost":false,"isSelf":false,"isSkipSelf":false,"isOptional":false,"token":{"identifier":{"reference":{"__symbol":11,"members":[]}}}},{"isAttribute":false,"isHost":false,"isSelf":false,"isSkipSelf":false,"isOptional":false,"token":{"identifier":{"reference":{"__symbol":12,"members":[]}}}},{"isAttribute":false,"isHost":false,"isSelf":false,"isSkipSelf":false,"isOptional":false,"token":{"identifier":{"reference":{"__symbol":13,"members":[]}}}},{"isAttribute":false,"isHost":false,"isSelf":false,"isSkipSelf":false,"isOptional":false,"token":{"identifier":{"reference":{"__symbol":14,"members":[]}}}},{"isAttribute":false,"isHost":false,"isSelf":false,"isSkipSelf":false,"isOptional":true,"token":{"identifier":{"reference":{"__symbol":15,"members":[]}}}},{"isAttribute":false,"isHost":false,"isSelf":false,"isSkipSelf":false,"isOptional":true,"token":{"identifier":{"reference":{"__symbol":16,"members":[]}}}}],"lifecycleHooks":[1]}},"useClass":{"reference":{"__symbol":8,"members":[]},"diDeps":[{"isAttribute":false,"isHost":false,"isSelf":false,"isSkipSelf":false,"isOptional":false,"token":{"identifier":{"reference":{"__symbol":9,"members":[]}}}},{"isAttribute":false,"isHost":false,"isSelf":false,"isSkipSelf":false,"isOptional":false,"token":{"identifier":{"reference":{"__symbol":10,"members":[]}}}},{"isAttribute":false,"isHost":false,"isSelf":false,"isSkipSelf":false,"isOptional":false,"token":{"identifier":{"reference":{"__symbol":11,"members":[]}}}},{"isAttribute":false,"isHost":false,"isSelf":false,"isSkipSelf":false,"isOptional":false,"token":{"identifier":{"reference":{"__symbol":12,"members":[]}}}},{"isAttribute":false,"isHost":false,"isSelf":false,"isSkipSelf":false,"isOptional":false,"token":{"identifier":{"reference":{"__symbol":13,"members":[]}}}},{"isAttribute":false,"isHost":false,"isSelf":false,"isSkipSelf":false,"isOptional":false,"token":{"identifier":{"reference":{"__symbol":14,"members":[]}}}},{"isAttribute":false,"isHost":false,"isSelf":false,"isSkipSelf":false,"isOptional":true,"token":{"identifier":{"reference":{"__symbol":15,"members":[]}}}},{"isAttribute":false,"isHost":false,"isSelf":false,"isSkipSelf":false,"isOptional":true,"token":{"identifier":{"reference":{"__symbol":16,"members":[]}}}}],"lifecycleHooks":[1]},"useFactory":null,"useExisting":null,"deps":[{"isAttribute":false,"isHost":false,"isSelf":false,"isSkipSelf":false,"isOptional":false,"token":{"identifier":{"reference":{"__symbol":9,"members":[]}}}},{"isAttribute":false,"isHost":false,"isSelf":false,"isSkipSelf":false,"isOptional":false,"token":{"identifier":{"reference":{"__symbol":10,"members":[]}}}},{"isAttribute":false,"isHost":false,"isSelf":false,"isSkipSelf":false,"isOptional":false,"token":{"identifier":{"reference":{"__symbol":11,"members":[]}}}},{"isAttribute":false,"isHost":false,"isSelf":false,"isSkipSelf":false,"isOptional":false,"token":{"identifier":{"reference":{"__symbol":12,"members":[]}}}},{"isAttribute":false,"isHost":false,"isSelf":false,"isSkipSelf":false,"isOptional":false,"token":{"identifier":{"reference":{"__symbol":13,"members":[]}}}},{"isAttribute":false,"isHost":false,"isSelf":false,"isSkipSelf":false,"isOptional":false,"token":{"identifier":{"reference":{"__symbol":14,"members":[]}}}},{"isAttribute":false,"isHost":false,"isSelf":false,"isSkipSelf":false,"isOptional":true,"token":{"identifier":{"reference":{"__symbol":15,"members":[]}}}},{"isAttribute":false,"isHost":false,"isSelf":false,"isSkipSelf":false,"isOptional":true,"token":{"identifier":{"reference":{"__symbol":16,"members":[]}}}}],"multi":false},"module":{"reference":{"__symbol":17,"members":[]},"diDeps":[],"lifecycleHooks":[]}},{"provider":{"token":{"identifier":{"reference":{"__symbol":18,"members":[]}}},"useClass":null,"useFactory":null,"useExisting":{"identifier":{"reference":{"__symbol":8,"members":[]}}},"multi":false},"module":{"reference":{"__symbol":17,"members":[]},"diDeps":[],"lifecycleHooks":[]}},{"provider":{"token":{"identifier":{"reference":{"__symbol":14,"members":[]},"diDeps":[{"isAttribute":false,"isHost":false,"isSelf":false,"isSkipSelf":false,"isOptional":true,"token":{"identifier":{"reference":{"__symbol":19,"members":[]}}}}],"lifecycleHooks":[]}},"useClass":{"reference":{"__symbol":14,"members":[]},"diDeps":[{"isAttribute":false,"isHost":false,"isSelf":false,"isSkipSelf":false,"isOptional":true,"token":{"identifier":{"reference":{"__symbol":19,"members":[]}}}}],"lifecycleHooks":[]},"useFactory":null,"useExisting":null,"deps":[{"isAttribute":false,"isHost":false,"isSelf":false,"isSkipSelf":false,"isOptional":true,"token":{"identifier":{"reference":{"__symbol":19,"members":[]}}}}],"multi":false},"module":{"reference":{"__symbol":17,"members":[]},"diDeps":[],"lifecycleHooks":[]}},{"provider":{"token":{"identifier":{"reference":{"__symbol":20,"members":[]},"diDeps":[],"lifecycleHooks":[]}},"useClass":{"reference":{"__symbol":20,"members":[]},"diDeps":[],"lifecycleHooks":[]},"useFactory":null,"useExisting":null,"deps":[],"multi":false},"module":{"reference":{"__symbol":17,"members":[]},"diDeps":[],"lifecycleHooks":[]}},{"provider":{"token":{"identifier":{"reference":{"__symbol":21,"members":[]}}},"useClass":null,"useFactory":{"reference":{"__symbol":22,"members":[]},"diDeps":[]},"useExisting":null,"deps":[],"multi":false},"module":{"reference":{"__symbol":17,"members":[]},"diDeps":[],"lifecycleHooks":[]}},{"provider":{"token":{"identifier":{"reference":{"__symbol":23,"members":[]},"diDeps":[{"isAttribute":false,"isHost":false,"isSelf":false,"isSkipSelf":false,"isOptional":false,"token":{"identifier":{"reference":{"__symbol":24,"members":[]}}}},{"isAttribute":false,"isHost":false,"isSelf":false,"isSkipSelf":false,"isOptional":false,"token":{"identifier":{"reference":{"__symbol":25,"members":[]}}}},{"isAttribute":false,"isHost":false,"isSelf":false,"isSkipSelf":false,"isOptional":false,"token":{"identifier":{"reference":{"__symbol":26,"members":[]}}}}],"lifecycleHooks":[]}},"useClass":{"reference":{"__symbol":23,"members":[]},"diDeps":[{"isAttribute":false,"isHost":false,"isSelf":false,"isSkipSelf":false,"isOptional":false,"token":{"identifier":{"reference":{"__symbol":24,"members":[]}}}},{"isAttribute":false,"isHost":false,"isSelf":false,"isSkipSelf":false,"isOptional":false,"token":{"identifier":{"reference":{"__symbol":25,"members":[]}}}},{"isAttribute":false,"isHost":false,"isSelf":false,"isSkipSelf":false,"isOptional":false,"token":{"identifier":{"reference":{"__symbol":26,"members":[]}}}}],"lifecycleHooks":[]},"useFactory":null,"useExisting":null,"deps":[{"isAttribute":false,"isHost":false,"isSelf":false,"isSkipSelf":false,"isOptional":false,"token":{"identifier":{"reference":{"__symbol":24,"members":[]}}}},{"isAttribute":false,"isHost":false,"isSelf":false,"isSkipSelf":false,"isOptional":false,"token":{"identifier":{"reference":{"__symbol":25,"members":[]}}}},{"isAttribute":false,"isHost":false,"isSelf":false,"isSkipSelf":false,"isOptional":false,"token":{"identifier":{"reference":{"__symbol":26,"members":[]}}}}],"multi":false},"module":{"reference":{"__symbol":17,"members":[]},"diDeps":[],"lifecycleHooks":[]}},{"provider":{"token":{"identifier":{"reference":{"__symbol":26,"members":[]},"diDeps":[{"isAttribute":false,"isHost":false,"isSelf":false,"isSkipSelf":false,"isOptional":false,"token":{"identifier":{"reference":{"__symbol":9,"members":[]}}}}],"lifecycleHooks":[]}},"useClass":{"reference":{"__symbol":26,"members":[]},"diDeps":[{"isAttribute":false,"isHost":false,"isSelf":false,"isSkipSelf":false,"isOptional":false,"token":{"identifier":{"reference":{"__symbol":9,"members":[]}}}}],"lifecycleHooks":[]},"useFactory":null,"useExisting":null,"deps":[{"isAttribute":false,"isHost":false,"isSelf":false,"isSkipSelf":false,"isOptional":false,"token":{"identifier":{"reference":{"__symbol":9,"members":[]}}}}],"multi":false},"module":{"reference":{"__symbol":17,"members":[]},"diDeps":[],"lifecycleHooks":[]}},{"provider":{"token":{"identifier":{"reference":{"__symbol":27,"members":[]}}},"useClass":null,"useFactory":{"reference":{"__symbol":28,"members":[]},"diDeps":[]},"useExisting":null,"deps":[],"multi":false},"module":{"reference":{"__symbol":17,"members":[]},"diDeps":[],"lifecycleHooks":[]}},{"provider":{"token":{"identifier":{"reference":{"__symbol":29,"members":[]}}},"useClass":null,"useFactory":{"reference":{"__symbol":30,"members":[]},"diDeps":[]},"useExisting":null,"deps":[],"multi":false},"module":{"reference":{"__symbol":17,"members":[]},"diDeps":[],"lifecycleHooks":[]}},{"provider":{"token":{"identifier":{"reference":{"__symbol":6,"members":[]}}},"useClass":null,"useFactory":{"reference":{"__symbol":31,"members":[]},"diDeps":[{"isAttribute":false,"isHost":false,"isSelf":false,"isSkipSelf":true,"isOptional":true,"token":{"identifier":{"reference":{"__symbol":6,"members":[]}}}}]},"useExisting":null,"deps":[{"isAttribute":false,"isHost":false,"isSelf":false,"isSkipSelf":true,"isOptional":true,"token":{"identifier":{"reference":{"__symbol":6,"members":[]}}}}],"multi":false},"module":{"reference":{"__symbol":17,"members":[]},"diDeps":[],"lifecycleHooks":[]}},{"provider":{"token":{"identifier":{"reference":{"__symbol":32,"members":[]},"diDeps":[{"isAttribute":false,"isHost":false,"isSelf":false,"isSkipSelf":false,"isOptional":false,"token":{"identifier":{"reference":{"__symbol":33,"members":[]}}}},{"isAttribute":false,"isHost":false,"isSelf":false,"isSkipSelf":false,"isOptional":false,"token":{"identifier":{"reference":{"__symbol":34,"members":[]}}}},{"isAttribute":false,"isHost":false,"isSelf":false,"isSkipSelf":false,"isOptional":false,"token":{"identifier":{"reference":{"__symbol":35,"members":[]}}}},{"isAttribute":false,"isHost":false,"isSelf":false,"isSkipSelf":false,"isOptional":false,"token":{"identifier":{"reference":{"__symbol":36,"members":[]}}}}],"lifecycleHooks":[]}},"useClass":{"reference":{"__symbol":32,"members":[]},"diDeps":[{"isAttribute":false,"isHost":false,"isSelf":false,"isSkipSelf":false,"isOptional":false,"token":{"identifier":{"reference":{"__symbol":33,"members":[]}}}},{"isAttribute":false,"isHost":false,"isSelf":false,"isSkipSelf":false,"isOptional":false,"token":{"identifier":{"reference":{"__symbol":34,"members":[]}}}},{"isAttribute":false,"isHost":false,"isSelf":false,"isSkipSelf":false,"isOptional":false,"token":{"identifier":{"reference":{"__symbol":35,"members":[]}}}},{"isAttribute":false,"isHost":false,"isSelf":false,"isSkipSelf":false,"isOptional":false,"token":{"identifier":{"reference":{"__symbol":36,"members":[]}}}}],"lifecycleHooks":[]},"useFactory":null,"useExisting":null,"deps":[{"isAttribute":false,"isHost":false,"isSelf":false,"isSkipSelf":false,"isOptional":false,"token":{"identifier":{"reference":{"__symbol":33,"members":[]}}}},{"isAttribute":false,"isHost":false,"isSelf":false,"isSkipSelf":false,"isOptional":false,"token":{"identifier":{"reference":{"__symbol":34,"members":[]}}}},{"isAttribute":false,"isHost":false,"isSelf":false,"isSkipSelf":false,"isOptional":false,"token":{"identifier":{"reference":{"__symbol":35,"members":[]}}}},{"isAttribute":false,"isHost":false,"isSelf":false,"isSkipSelf":false,"isOptional":false,"token":{"identifier":{"reference":{"__symbol":36,"members":[]}}}}],"multi":false},"module":{"reference":{"__symbol":37,"members":[]},"diDeps":[],"lifecycleHooks":[]}},{"provider":{"token":{"identifier":{"reference":{"__symbol":24,"members":[]}}},"useClass":null,"useFactory":null,"useExisting":{"identifier":{"reference":{"__symbol":32,"members":[]}}},"multi":false},"module":{"reference":{"__symbol":37,"members":[]},"diDeps":[],"lifecycleHooks":[]}},{"provider":{"token":{"identifier":{"reference":{"__symbol":34,"members":[]}}},"useClass":null,"useFactory":{"reference":{"__symbol":38,"members":[]},"diDeps":[{"isAttribute":false,"isHost":false,"isSelf":false,"isSkipSelf":false,"isOptional":false,"token":{"identifier":{"reference":{"__symbol":9,"members":[]}}}}]},"useExisting":null,"deps":[{"isAttribute":false,"isHost":false,"isSelf":false,"isSkipSelf":false,"isOptional":false,"token":{"identifier":{"reference":{"__symbol":9,"members":[]}}}}],"multi":false},"module":{"reference":{"__symbol":37,"members":[]},"diDeps":[],"lifecycleHooks":[]}},{"provider":{"token":{"identifier":{"reference":{"__symbol":33,"members":[]}}},"useClass":{"reference":{"__symbol":39,"members":[]},"diDeps":[{"isAttribute":false,"isHost":false,"isSelf":false,"isSkipSelf":false,"isOptional":false,"token":{"identifier":{"reference":{"__symbol":34,"members":[]}}}},{"isAttribute":false,"isHost":false,"isSelf":false,"isSkipSelf":false,"isOptional":false,"token":{"identifier":{"reference":{"__symbol":35,"members":[]}}}}],"lifecycleHooks":[]},"useFactory":null,"useExisting":null,"deps":[{"isAttribute":false,"isHost":false,"isSelf":false,"isSkipSelf":false,"isOptional":false,"token":{"identifier":{"reference":{"__symbol":34,"members":[]}}}},{"isAttribute":false,"isHost":false,"isSelf":false,"isSkipSelf":false,"isOptional":false,"token":{"identifier":{"reference":{"__symbol":35,"members":[]}}}}],"multi":false},"module":{"reference":{"__symbol":37,"members":[]},"diDeps":[],"lifecycleHooks":[]}},{"provider":{"token":{"identifier":{"reference":{"__symbol":40,"members":[]}}},"useClass":{"reference":{"__symbol":41,"members":[]},"diDeps":[{"isAttribute":false,"isHost":false,"isSelf":false,"isSkipSelf":false,"isOptional":false,"token":{"identifier":{"reference":{"__symbol":34,"members":[]}}}},{"isAttribute":false,"isHost":false,"isSelf":false,"isSkipSelf":false,"isOptional":false,"token":{"identifier":{"reference":{"__symbol":35,"members":[]}}}}],"lifecycleHooks":[]},"useFactory":null,"useExisting":null,"deps":[{"isAttribute":false,"isHost":false,"isSelf":false,"isSkipSelf":false,"isOptional":false,"token":{"identifier":{"reference":{"__symbol":34,"members":[]}}}},{"isAttribute":false,"isHost":false,"isSelf":false,"isSkipSelf":false,"isOptional":false,"token":{"identifier":{"reference":{"__symbol":35,"members":[]}}}}],"multi":false},"module":{"reference":{"__symbol":37,"members":[]},"diDeps":[],"lifecycleHooks":[]}},{"provider":{"token":{"identifier":{"reference":{"__symbol":42,"members":[]},"diDeps":[],"lifecycleHooks":[]}},"useClass":{"reference":{"__symbol":42,"members":[]},"diDeps":[],"lifecycleHooks":[]},"useFactory":null,"useExisting":null,"deps":[],"multi":false},"module":{"reference":{"__symbol":37,"members":[]},"diDeps":[],"lifecycleHooks":[]}},{"provider":{"token":{"identifier":{"reference":{"__symbol":25,"members":[]}}},"useClass":null,"useFactory":null,"useExisting":{"identifier":{"reference":{"__symbol":43,"members":[]}}},"multi":false},"module":{"reference":{"__symbol":37,"members":[]},"diDeps":[],"lifecycleHooks":[]}},{"provider":{"token":{"identifier":{"reference":{"__symbol":43,"members":[]}}},"useClass":{"reference":{"__symbol":44,"members":[]},"diDeps":[],"lifecycleHooks":[]},"useFactory":null,"useExisting":null,"deps":[],"multi":false},"module":{"reference":{"__symbol":37,"members":[]},"diDeps":[],"lifecycleHooks":[]}},{"provider":{"token":{"identifier":{"reference":{"__symbol":2,"members":[]}}},"useClass":null,"useFactory":{"reference":{"__symbol":45,"members":[]},"diDeps":[{"isAttribute":false,"isHost":false,"isSelf":false,"isSkipSelf":false,"isOptional":false,"token":{"identifier":{"reference":{"__symbol":46,"members":[]}}}}]},"useExisting":null,"deps":[{"isAttribute":false,"isHost":false,"isSelf":false,"isSkipSelf":false,"isOptional":false,"token":{"identifier":{"reference":{"__symbol":46,"members":[]}}}}],"multi":false},"module":{"reference":{"__symbol":37,"members":[]},"diDeps":[],"lifecycleHooks":[]}},{"provider":{"token":{"identifier":{"reference":{"__symbol":12,"members":[]}}},"useClass":null,"useFactory":{"reference":{"__symbol":47,"members":[]},"diDeps":[]},"useExisting":null,"deps":[],"multi":false},"module":{"reference":{"__symbol":37,"members":[]},"diDeps":[],"lifecycleHooks":[]}},{"provider":{"token":{"identifier":{"reference":{"__symbol":48,"members":[]}}},"useClass":null,"useFactory":{"reference":{"__symbol":49,"members":[]},"diDeps":[{"isAttribute":false,"isHost":false,"isSelf":false,"isSkipSelf":false,"isOptional":false,"token":{"identifier":{"reference":{"__symbol":24,"members":[]}}}}]},"useExisting":null,"deps":[{"isAttribute":false,"isHost":false,"isSelf":false,"isSkipSelf":false,"isOptional":false,"token":{"identifier":{"reference":{"__symbol":24,"members":[]}}}}],"multi":true},"module":{"reference":{"__symbol":37,"members":[]},"diDeps":[],"lifecycleHooks":[]}},{"provider":{"token":{"identifier":{"reference":{"__symbol":19,"members":[]}}},"useClass":null,"useFactory":{"reference":{"__symbol":50,"members":[]},"diDeps":[{"isAttribute":false,"isHost":false,"isSelf":false,"isSkipSelf":false,"isOptional":false,"token":{"identifier":{"reference":{"__symbol":9,"members":[]}}}},{"isAttribute":false,"isHost":false,"isSelf":false,"isSkipSelf":false,"isOptional":false,"token":{"identifier":{"reference":{"__symbol":24,"members":[]}}}}]},"useExisting":null,"deps":[{"isAttribute":false,"isHost":false,"isSelf":false,"isSkipSelf":false,"isOptional":false,"token":{"identifier":{"reference":{"__symbol":9,"members":[]}}}},{"isAttribute":false,"isHost":false,"isSelf":false,"isSkipSelf":false,"isOptional":false,"token":{"identifier":{"reference":{"__symbol":24,"members":[]}}}}],"multi":true},"module":{"reference":{"__symbol":37,"members":[]},"diDeps":[],"lifecycleHooks":[]}},{"provider":{"token":{"identifier":{"reference":{"__symbol":51,"members":[]}}},"useClass":null,"useValue":{"id":"main","options":{}},"useFactory":null,"useExisting":null,"multi":false},"module":{"reference":{"__symbol":1,"members":[]},"diDeps":[{"isAttribute":false,"isHost":false,"isSelf":false,"isSkipSelf":false,"isOptional":false,"token":{"identifier":{"reference":{"__symbol":2,"members":[]}}}}],"lifecycleHooks":[]}}],"modules":[{"reference":{"__symbol":7,"members":[]},"diDeps":[],"lifecycleHooks":[]},{"reference":{"__symbol":17,"members":[]},"diDeps":[],"lifecycleHooks":[]},{"reference":{"__symbol":37,"members":[]},"diDeps":[],"lifecycleHooks":[]},{"reference":{"__symbol":1,"members":[]},"diDeps":[{"isAttribute":false,"isHost":false,"isSelf":false,"isSkipSelf":false,"isOptional":false,"token":{"identifier":{"reference":{"__symbol":2,"members":[]}}}}],"lifecycleHooks":[]}],"exportedDirectives":[],"exportedPipes":[]}}],"symbols":[{"__symbol":0,"name":"DemoAppView","filePath":"/Users/robwormald/Dev/angular/angular-electron/modules/demo-app/demo-app.d.ts"},{"__symbol":1,"name":"ElectronDemoApp","filePath":"/Users/robwormald/Dev/angular/angular-electron/modules/demo-app/demo-app.d.ts"},{"__symbol":2,"name":"ElectronAppRef","filePath":"/Users/robwormald/Dev/angular/angular-electron/modules/platform-electron/src/shared/electron_app_ref.d.ts"},{"__symbol":3,"name":"DemoAppViewNgFactory","filePath":"/Users/robwormald/Dev/angular/angular-electron/modules/demo-app/demo-app.ngfactory.d.ts"},{"__symbol":4,"name":"NgLocalization","filePath":"/Users/robwormald/Dev/angular/angular-electron/node_modules/@angular/common/src/localization.d.ts"},{"__symbol":5,"name":"NgLocaleLocalization","filePath":"/Users/robwormald/Dev/angular/angular-electron/node_modules/@angular/common/src/localization.d.ts"},{"__symbol":6,"name":"LOCALE_ID","filePath":"/Users/robwormald/Dev/angular/angular-electron/node_modules/@angular/core/src/i18n/tokens.d.ts"},{"__symbol":7,"name":"CommonModule","filePath":"/Users/robwormald/Dev/angular/angular-electron/node_modules/@angular/common/src/common_module.d.ts"},{"__symbol":8,"name":"ApplicationRef_","filePath":"/Users/robwormald/Dev/angular/angular-electron/node_modules/@angular/core/src/application_ref.d.ts"},{"__symbol":9,"name":"NgZone","filePath":"/Users/robwormald/Dev/angular/angular-electron/node_modules/@angular/core/src/zone/ng_zone.d.ts"},{"__symbol":10,"name":"Console","filePath":"/Users/robwormald/Dev/angular/angular-electron/node_modules/@angular/core/src/console.d.ts"},{"__symbol":11,"name":"Injector","filePath":"/Users/robwormald/Dev/angular/angular-electron/node_modules/@angular/core/src/di/injector.d.ts"},{"__symbol":12,"name":"ErrorHandler","filePath":"/Users/robwormald/Dev/angular/angular-electron/node_modules/@angular/core/src/error_handler.d.ts"},{"__symbol":13,"name":"ComponentFactoryResolver","filePath":"/Users/robwormald/Dev/angular/angular-electron/node_modules/@angular/core/src/linker/component_factory_resolver.d.ts"},{"__symbol":14,"name":"ApplicationInitStatus","filePath":"/Users/robwormald/Dev/angular/angular-electron/node_modules/@angular/core/src/application_init.d.ts"},{"__symbol":15,"name":"TestabilityRegistry","filePath":"/Users/robwormald/Dev/angular/angular-electron/node_modules/@angular/core/src/testability/testability.d.ts"},{"__symbol":16,"name":"Testability","filePath":"/Users/robwormald/Dev/angular/angular-electron/node_modules/@angular/core/src/testability/testability.d.ts"},{"__symbol":17,"name":"ApplicationModule","filePath":"/Users/robwormald/Dev/angular/angular-electron/node_modules/@angular/core/src/application_module.d.ts"},{"__symbol":18,"name":"ApplicationRef","filePath":"/Users/robwormald/Dev/angular/angular-electron/node_modules/@angular/core/src/application_ref.d.ts"},{"__symbol":19,"name":"APP_INITIALIZER","filePath":"/Users/robwormald/Dev/angular/angular-electron/node_modules/@angular/core/src/application_init.d.ts"},{"__symbol":20,"name":"Compiler","filePath":"/Users/robwormald/Dev/angular/angular-electron/node_modules/@angular/core/src/linker/compiler.d.ts"},{"__symbol":21,"name":"APP_ID","filePath":"/Users/robwormald/Dev/angular/angular-electron/node_modules/@angular/core/src/application_tokens.d.ts"},{"__symbol":22,"name":"_appIdRandomProviderFactory","filePath":"/Users/robwormald/Dev/angular/angular-electron/node_modules/@angular/core/src/application_tokens.d.ts"},{"__symbol":23,"name":"ViewUtils","filePath":"/Users/robwormald/Dev/angular/angular-electron/node_modules/@angular/core/src/linker/view_utils.d.ts"},{"__symbol":24,"name":"RootRenderer","filePath":"/Users/robwormald/Dev/angular/angular-electron/node_modules/@angular/core/src/render/api.d.ts"},{"__symbol":25,"name":"Sanitizer","filePath":"/Users/robwormald/Dev/angular/angular-electron/node_modules/@angular/core/src/security.d.ts"},{"__symbol":26,"name":"AnimationQueue","filePath":"/Users/robwormald/Dev/angular/angular-electron/node_modules/@angular/core/src/animation/animation_queue.d.ts"},{"__symbol":27,"name":"IterableDiffers","filePath":"/Users/robwormald/Dev/angular/angular-electron/node_modules/@angular/core/src/change_detection/differs/iterable_differs.d.ts"},{"__symbol":28,"name":"_iterableDiffersFactory","filePath":"/Users/robwormald/Dev/angular/angular-electron/node_modules/@angular/core/src/application_module.d.ts"},{"__symbol":29,"name":"KeyValueDiffers","filePath":"/Users/robwormald/Dev/angular/angular-electron/node_modules/@angular/core/src/change_detection/differs/keyvalue_differs.d.ts"},{"__symbol":30,"name":"_keyValueDiffersFactory","filePath":"/Users/robwormald/Dev/angular/angular-electron/node_modules/@angular/core/src/application_module.d.ts"},{"__symbol":31,"name":"_localeFactory","filePath":"/Users/robwormald/Dev/angular/angular-electron/node_modules/@angular/core/src/application_module.d.ts"},{"__symbol":32,"name":"ElectronRootRenderer","filePath":"/Users/robwormald/Dev/angular/angular-electron/modules/platform-electron/src/main/renderer.d.ts"},{"__symbol":33,"name":"ClientMessageBrokerFactory","filePath":"/Users/robwormald/Dev/angular/angular-electron/modules/platform-electron/src/shared/client_message_broker.d.ts"},{"__symbol":34,"name":"ElectronMessageBus","filePath":"/Users/robwormald/Dev/angular/angular-electron/modules/platform-electron/src/shared/message_bus.d.ts"},{"__symbol":35,"name":"Serializer","filePath":"/Users/robwormald/Dev/angular/angular-electron/modules/platform-electron/src/shared/serializer.d.ts"},{"__symbol":36,"name":"RenderStore","filePath":"/Users/robwormald/Dev/angular/angular-electron/modules/platform-electron/src/shared/render_store.d.ts"},{"__symbol":37,"name":"ElectronMainModule","filePath":"/Users/robwormald/Dev/angular/angular-electron/modules/platform-electron/src/electron_main.d.ts"},{"__symbol":38,"name":"createMainRenderBus","filePath":"/Users/robwormald/Dev/angular/angular-electron/modules/platform-electron/src/shared/electron_ipc_message_bus.d.ts"},{"__symbol":39,"name":"ClientMessageBrokerFactory_","filePath":"/Users/robwormald/Dev/angular/angular-electron/modules/platform-electron/src/shared/client_message_broker.d.ts"},{"__symbol":40,"name":"ServiceMessageBrokerFactory","filePath":"/Users/robwormald/Dev/angular/angular-electron/modules/platform-electron/src/shared/service_message_broker.d.ts"},{"__symbol":41,"name":"ServiceMessageBrokerFactory_","filePath":"/Users/robwormald/Dev/angular/angular-electron/modules/platform-electron/src/shared/service_message_broker.d.ts"},{"__symbol":42,"name":"ElectronRendererManager","filePath":"/Users/robwormald/Dev/angular/angular-electron/modules/platform-electron/src/main/renderer_manager.d.ts"},{"__symbol":43,"name":"DomSanitizer","filePath":"/Users/robwormald/Dev/angular/angular-electron/node_modules/@angular/platform-browser/src/security/dom_sanitization_service.d.ts"},{"__symbol":44,"name":"DomSanitizerImpl","filePath":"/Users/robwormald/Dev/angular/angular-electron/node_modules/@angular/platform-browser/src/security/dom_sanitization_service.d.ts"},{"__symbol":45,"name":"createElectronAppRef","filePath":"/Users/robwormald/Dev/angular/angular-electron/modules/platform-electron/src/electron_main.d.ts"},{"__symbol":46,"name":"PlatformRef","filePath":"/Users/robwormald/Dev/angular/angular-electron/node_modules/@angular/core/src/application_ref.d.ts"},{"__symbol":47,"name":"errorHandler","filePath":"/Users/robwormald/Dev/angular/angular-electron/modules/platform-electron/src/electron_main.d.ts"},{"__symbol":48,"name":"APP_BOOTSTRAP_LISTENER","filePath":"/Users/robwormald/Dev/angular/angular-electron/node_modules/@angular/core/src/application_tokens.d.ts"},{"__symbol":49,"name":"waitForElectronAppReady","filePath":"/Users/robwormald/Dev/angular/angular-electron/modules/platform-electron/src/electron_main.d.ts"},{"__symbol":50,"name":"setUpRenderFlushing","filePath":"/Users/robwormald/Dev/angular/angular-electron/modules/platform-electron/src/electron_main.d.ts"},{"__symbol":51,"name":"ELECTRON_WINDOW","filePath":"/Users/robwormald/Dev/angular/angular-electron/modules/platform-electron/src/platform-electron.d.ts"},{"__symbol":52,"name":"Wrapper_DemoAppView","filePath":"/Users/robwormald/Dev/angular/angular-electron/modules/demo-app/demo-app.ngfactory.d.ts"},{"__symbol":53,"name":"View_DemoAppView_0","filePath":"/Users/robwormald/Dev/angular/angular-electron/modules/demo-app/demo-app.ngfactory.d.ts"}]}